motley/__init__.py
motley-0.0.1.dist-info/LICENSE
motley-0.0.1.dist-info/METADATA
motley-0.0.1.dist-info/WHEEL
motley-0.0.1.dist-info/top_level.txt
motley-0.0.1.dist-info/RECORD
