Metadata-Version: 2.1
Name: motley
Version: 0.0.1
Summary: motley code catalog
Home-page: https://github.com/frootlab/motley
Author: frootlab
Author-email: frootlab@gmail.com
License: GPLv3
Keywords: catalog catalog-software
Platform: UNKNOWN
Classifier: Development Status :: 1 - Planning
Classifier: Intended Audience :: Developers
Classifier: Intended Audience :: Science/Research
Classifier: License :: OSI Approved :: GNU General Public License v3 (GPLv3)
Classifier: Programming Language :: Python :: 3
Classifier: Programming Language :: Python :: 3.7
Classifier: Operating System :: OS Independent
Classifier: Topic :: Internet :: WWW/HTTP :: Dynamic Content
Classifier: Topic :: Software Development :: Libraries :: Python Modules
Requires-Python: >=3.7
Requires-Dist: numpy (>=1.15)
Requires-Dist: flib (>=0.9)
Requires-Dist: pandb (>=0.1.8)
Requires-Dist: nemoa (>=0.5.581)
